poetry_scaffold_plugin/__init__.py
poetry_scaffold_plugin/plugins.py
poetry_scaffold_plugin/templates/.gitignore
poetry_scaffold_plugin/templates/.pre-commit-config.yaml
poetry_scaffold_plugin/templates/pyproject.toml
poetry_scaffold_plugin/templates/setup.cfg
poetry_scaffold_plugin-0.1.0.dist-info/entry_points.txt
poetry_scaffold_plugin-0.1.0.dist-info/LICENSE
poetry_scaffold_plugin-0.1.0.dist-info/WHEEL
poetry_scaffold_plugin-0.1.0.dist-info/METADATA
poetry_scaffold_plugin-0.1.0.dist-info/RECORD
