Metadata-Version: 2.1
Name: poetry-scaffold-plugin
Version: 0.1.0
Summary: Poetry plugin that installs and configures dev dependencies, so you don't have to.
License: MIT
Author: Ellen Potter
Author-email: 38250543+ellen364@users.noreply.github.com
Requires-Python: >=3.8,<4.0
Classifier: License :: OSI Approved :: MIT License
Classifier: Programming Language :: Python :: 3
Classifier: Programming Language :: Python :: 3.8
Classifier: Programming Language :: Python :: 3.9
Classifier: Programming Language :: Python :: 3.10
Requires-Dist: cleo (>=1.0.0a4,<2.0.0)
Requires-Dist: poetry (>=1.2.0a2,<2.0.0)
Requires-Dist: tomlkit (>=0.8.0,<0.9.0)
